Metadata-Version: 2.1
Name: dify_plugin_mod_by_spance
Version: 0.0.1b74
Summary: Dify Plugin SDK
Keywords: dify,plugin,sdk
Author-Email: langgenius <hello@dify.ai>
License: Apache2.0
Project-URL: Homepage, https://github.com/langgenius/dify-plugin-sdks.git
Requires-Python: >=3.11
Requires-Dist: Flask~=3.0.3
Requires-Dist: Werkzeug~=3.0.3
Requires-Dist: dpkt~=1.9.8
Requires-Dist: gevent~=24.11.1
Requires-Dist: httpx~=0.27.0
Requires-Dist: pydantic_settings~=2.3.4
Requires-Dist: pydantic~=2.8.2
Requires-Dist: pydub~=0.25.1
Requires-Dist: pyyaml~=6.0.1
Requires-Dist: requests~=2.32.3
Requires-Dist: socksio==1.0.0
Requires-Dist: tiktoken~=0.8.0
Requires-Dist: yarl>=1.9.4
